doxygen_junit.py
doxygen_junit-2.3.0.data/scripts/doxygen_junit.py
doxygen_junit-2.3.0.dist-info/LICENSE.txt
doxygen_junit-2.3.0.dist-info/METADATA
doxygen_junit-2.3.0.dist-info/WHEEL
doxygen_junit-2.3.0.dist-info/entry_points.txt
doxygen_junit-2.3.0.dist-info/top_level.txt
doxygen_junit-2.3.0.dist-info/RECORD
