Metadata-Version: 2.1
Name: doxygen-junit
Version: 2.3.0
Summary: Converts doxygen errors and warnings to JUnit XML format.
Home-page: https://github.com/johnthagen/doxygen-junit
Author: John Hagen
Author-email: johnthagen@gmail.com
License: MIT
Keywords: doxygen C C++ JUnit
Platform: UNKNOWN
Classifier: Development Status :: 4 - Beta
Classifier: Environment :: Console
Classifier: Intended Audience :: Developers
Classifier: License :: OSI Approved :: MIT License
Classifier: Operating System :: OS Independent
Classifier: Programming Language :: C
Classifier: Programming Language :: C++
Classifier: Programming Language :: Python
Classifier: Programming Language :: Python :: 3
Classifier: Programming Language :: Python :: 3 :: Only
Classifier: Programming Language :: Python :: 3.7
Classifier: Programming Language :: Python :: 3.8
Classifier: Programming Language :: Python :: 3.9
Classifier: Programming Language :: Python :: 3.10
Classifier: Topic :: Documentation
Classifier: Topic :: Software Development :: Documentation
Classifier: Topic :: Software Development :: Quality Assurance
Requires-Python: >=3.7
License-File: LICENSE.txt
Requires-Dist: exitstatus (>=1.0.0)
